{
  "user_id": "usr-20260617160331",
  "name": "Prem",
  "age": 24,
  "age_group": "18-24",
  "gender": "male",
  "location": {
    "city": "Kolkata",
    "state": "",
    "currency": "INR"
  },
  "budget": {
    "total": 4800,
    "per_item_max": 1200,
    "flexibility_percent": 10
  },
  "style_preferences": {
    "categories": [
      "western"
    ],
    "avoid": [],
    "favorite_colors": [],
    "favorite_fabrics": [],
    "occasions": [
      "college",
      "casual",
      "office"
    ]
  },
  "body_profile": {},
  "photo_path": "",
  "created_at": "2026-06-17T10:33:31.761617+00:00",
  "last_active": "2026-06-17T10:33:31.761617+00:00"
}